{
  "collapse-filter": false,
  "search": "",
  "showTags": true,
  "showAttachments": true,
  "hideUnresolved": false,
  "showOrphans": true,
  "collapse-color-groups": false,
  "colorGroups": [
    {
      "query": "tag:#Lesson-Plan  ",
      "color": {
        "a": 1,
        "rgb": 14048348
      }
    }
  ],
  "collapse-display": false,
  "showArrow": false,
  "textFadeMultiplier": 0.8,
  "nodeSizeMultiplier": 1,
  "lineSizeMultiplier": 1,
  "collapse-forces": false,
  "centerStrength": 1,
  "repelStrength": 20,
  "linkStrength": 1,
  "linkDistance": 500,
  "scale": 0.6734827131612633,
  "close": true
}